{
 "PlatformInfo": {
  "Platform": {
   "Name": "Windows",
   "BasePlatform": "Windows",
   "Generator": "2022.1.0.8070"
  },
  "RootPaths": {
   "ProjectRoot": "../../../../../Lobber_Wwise/",
   "SourceFilesRoot": "../../../../../Lobber_Wwise/.cache/Windows/",
   "SoundBanksRoot": ".",
   "ExternalSourcesInputFile": "",
   "ExternalSourcesOutputRoot": "../../../../../Lobber_Wwise/GeneratedSoundBanks/Windows"
  },
  "DefaultAlign": "16",
  "Settings": {
   "AutoSoundBankDefinition": "false",
   "CopyLooseStreamedMediaFiles": "true",
   "SubFoldersForGeneratedFiles": "false",
   "RemoveUnusedGeneratedFiles": "true",
   "SourceControlGeneratedFiles": "false",
   "GenerateHeaderFile": "true",
   "GenerateContentTxtFile": "true",
   "GenerateMetadataXML": "true",
   "GenerateMetadataJSON": "true",
   "GenerateAllBanksMetadata": "true",
   "GeneratePerBankMetadata": "false",
   "UseSoundBankNames": "true",
   "AllowExceedingMaxSize": "false",
   "MaxAttenuationInfo": "true",
   "EstimatedDurationInfo": "true",
   "PrintObjectGuid": "false",
   "PrintObjectPath": "false"
  },
  "FileHash": "{CE5AA29C-6462-D595-0143-57302686345D}"
 }
}